{
  "swagger": "2.0",
  "info": {
    "version": "1.0.0",
    "title": "REST API",
    "description": ""
  },
  "host": "localhost:3000",
  "basePath": "/",
  "schemes": [
    "http"
  ],
  "paths": {
    "/": {
      "get": {
        "description": "Get all Products",
        "parameters": [],
        "responses": {
          "200": {
            "description": "OK"
          },
          "404": {
            "description": "Not Found"
          }
        }
      }
    },
    "/api/product/getAll": {
      "get": {
        "description": "Get all Products",
        "parameters": [],
        "responses": {
          "200": {
            "description": "OK"
          },
          "404": {
            "description": "Not Found"
          }
        }
      }
    },
    "/api/product/create": {
      "post": {
        "description": "Create a Product",
        "parameters": [{"productName": "Mechanical punch", "productOwnerName":"Smriti Shakdher","developers": ["Josh Rintoul","Jeffrey Joju","Rhiannon Herbert","James Elson"],"scrumMasterName": "Vasavi Kakkat", "startDate": "2023/01/25", "methodology": "Agile"}],
        "responses": {
          "200": {
            "description": "OK"
          },
          "500": {
            "description": "Internal Server Error"
          }
        }
      }
    },
    "/api/product/update/{id}": {
      "put": {
        "description": "Update a product",
        "parameters": [
          {
            "name": "id",
            "in": "path",
            "required": true,
            "type": "string"
          }
        ],
        "responses": {
          "200": {
            "description": "OK"
          },
          "500": {
            "description": "Internal Server Error"
          }
        }
      }
    },
    "/api/product/delete/{id}": {
      "delete": {
        "description": "Delete a product",
        "parameters": [
          {
            "name": "id",
            "in": "path",
            "required": true,
            "type": "string"
          }
        ],
        "responses": {
          "200": {
            "description": "OK"
          },
          "500": {
            "description": "Internal Server Error"
          }
        }
      }
    },
    "/api/product/search/{keyword}": {
      "get": {
        "description": "Search product list with the column of scrum master name and developers",
        "parameters": [
          {
            "name": "keyword",
            "in": "path",
            "required": true,
            "type": "string"
          }
        ],
        "responses": {
          "200": {
            "description": "OK"
          }
        }
      }
    }
  }
}